[
  {
    "href": "https://www.linkedin.com/in/jerry-chen-23a10511b/",
    "lines": [
      "Jerry Chen",
      "Focusing on ARM Embedded Edge Computer, Industrial Edge AI Controller ARMxy, Optional CPU, SOM, RS485/RS232/CAN/GPIO/DI/DO/AI/AO etc., Linux | Ubuntu | Node-Red | Python | IIoT | Support OEM ODM. Email: bl33@bliiot.com",
      "Connectie sinds 14 april 2026",
      "Bericht"
    ],
    "img_alts": [
      "Profielfoto van Jerry Chen"
    ],
    "card_tag": "DIV",
    "card_classes": "_6510336f _85909efa c708bb45 ee2a3463 _16deed48 _319f3287 dabaef03 db909906 dae014d9 df412571"
  },
  {
    "href": "https://www.linkedin.com/in/hassan-aloufi-827943288/",
    "lines": [
      "Hassan aloufi",
      "Electrical Engineer- Testing and commissioning engineer",
      "Connectie sinds 14 april 2026",
      "Bericht"
    ],
    "img_alts": [
      "Profielfoto van Hassan aloufi"
    ],
    "card_tag": "DIV",
    "card_classes": "_6510336f _85909efa c708bb45 ee2a3463 _16deed48 _319f3287 dabaef03 db909906 dae014d9 df412571"
  },
  {
    "href": "https://www.linkedin.com/in/matt-kurantowicz/",
    "lines": [
      "Matt Kurantowicz",
      "Building the future of industrial automation with AI | Educator",
      "Founder | Innovator in Industry 4.0",
      "Connectie sinds 13 april 2026",
      "Bericht"
    ],
    "img_alts": [
      "Profielfoto van Matt Kurantowicz"
    ],
    "card_tag": "DIV",
    "card_classes": "_6510336f _85909efa c708bb45 ee2a3463 _16deed48 _319f3287 dabaef03 db909906 dae014d9 df412571"
  },
  {
    "href": "https://www.linkedin.com/in/mohammad-shihab-a5a79627b/",
    "lines": [
      "Mohammad Shihab",
      "Network & System Administrator",
      "Connectie sinds 13 april 2026",
      "Bericht"
    ],
    "img_alts": [
      "Profielfoto van Mohammad Shihab"
    ],
    "card_tag": "DIV",
    "card_classes": "_6510336f _85909efa c708bb45 ee2a3463 _16deed48 _319f3287 dabaef03 db909906 dae014d9 df412571"
  }
]